MANIFEST.in
README.rst
chartjs.py
setup.py
chartjslib/__init__.py
chartjslib/modules/Chart.bundle.js
chartjslib/modules/Chart.bundle.min.js
chartjslib/modules/jquery.min.js
chartjslib/modules/utils.js
pychartjs.egg-info/PKG-INFO
pychartjs.egg-info/SOURCES.txt
pychartjs.egg-info/dependency_links.txt
pychartjs.egg-info/not-zip-safe
pychartjs.egg-info/top_level.txt