Metadata-Version: 1.1
Name: pychartjs
Version: 0.9.0
Summary: A chart.js wrapper
Home-page: https://github.com/peppicus/pychartjs.git
Author: peppicus
Author-email: homepeppicus@gmail.com
License: MIT
Keywords: web gui interface ajax web2.0 chart js
Platform: UNKNOWN
Classifier: Development Status :: 4 - Beta
Classifier: Intended Audience :: Developers
Classifier: Topic :: Software Development :: Build Tools
Classifier: License :: OSI Approved :: MIT License
Classifier: Programming Language :: Python :: 2
Classifier: Programming Language :: Python :: 2.6
Classifier: Programming Language :: Python :: 2.7
Classifier: Programming Language :: Python :: 3
Classifier: Programming Language :: Python :: 3.3
Classifier: Programming Language :: Python :: 3.4
Classifier: Programming Language :: Python :: 3.5
